airalogy/__init__.py
airalogy/airalogy/__init__.py
airalogy/assigner/__init__.py
airalogy/assigner/assigner_base.py
airalogy/assigner/assigner_result.py
airalogy/assigner/inline_assigner.py
airalogy/built_in_types/__init__.py
airalogy/built_in_types/aimd.py
airalogy/built_in_types/code_str.py
airalogy/built_in_types/current_time.py
airalogy/built_in_types/file.py
airalogy/built_in_types/ignore.py
airalogy/built_in_types/recommended.py
airalogy/built_in_types/user_name.py
airalogy/cli.py
airalogy/convert/__init__.py
airalogy/convert/markdown.py
airalogy/iso/__init__.py
airalogy/markdown/__init__.py
airalogy/markdown/ast_nodes.py
airalogy/markdown/errors.py
airalogy/markdown/get.py
airalogy/markdown/lexer.py
airalogy/markdown/model_generator.py
airalogy/markdown/parser.py
airalogy/markdown/tokens.py
airalogy/markdown/validator.py
airalogy/models/__init__.py
airalogy/models/check.py
airalogy/models/record.py
airalogy/models/step.py
airalogy/record/__init__.py
airalogy/record/hash.py
airalogy/record/validator.py
airalogy/types/__init__.py
airalogy/types/aimd.py
airalogy/types/atcg.py
airalogy/types/chinese.py
airalogy/types/code_str.py
airalogy/types/current.py
airalogy/types/file.py
airalogy/types/ignore.py
airalogy/types/protocol.py
airalogy/types/recommended.py
airalogy/types/user_name.py
airalogy-0.0.14.dist-info/WHEEL
airalogy-0.0.14.dist-info/entry_points.txt
airalogy-0.0.14.dist-info/METADATA
airalogy-0.0.14.dist-info/RECORD
