Metadata-Version: 2.3
Name: airalogy
Version: 0.0.14
Summary: The world's first universal framework for standardized data digitization
Author: Airalogy Team
License: Apache-2.0
Classifier: Development Status :: 4 - Beta
Classifier: Programming Language :: Python
Classifier: Programming Language :: Python :: 3.13
Classifier: Programming Language :: Python :: Implementation :: CPython
Requires-Dist: pydantic==2.12.3
Requires-Dist: httpx==0.28.1
Requires-Dist: isodate==0.7.2
Requires-Dist: markitdown[pdf,docx] ; extra == 'markitdown'
Requires-Python: >=3.13
Project-URL: Documentation, https://github.com/airalogy/airalogy#readme
Project-URL: Source, https://github.com/airalogy/airalogy
Provides-Extra: markitdown
